<annotation>
	<folder>Fölker</folder>
	<filename>5e95bac481e95.jpg</filename>
	<path>C:\Users\nickf\Desktop\Fölker-20210407T092910Z-001\Fölker\5e95bac481e95.jpg</path>
	<source>
		<database>Unknown</database>
	</source>
	<size>
		<width>800</width>
		<height>200</height>
		<depth>1</depth>
	</size>
	<segmented>0</segmented>
	<object>
		<name>s</name>
		<pose>Unspecified</pose>
		<truncated>0</truncated>
		<difficult>0</difficult>
		<bndbox>
			<xmin>181</xmin>
			<ymin>63</ymin>
			<xmax>254</xmax>
			<ymax>138</ymax>
		</bndbox>
	</object>
	<object>
		<name>l</name>
		<pose>Unspecified</pose>
		<truncated>0</truncated>
		<difficult>0</difficult>
		<bndbox>
			<xmin>255</xmin>
			<ymin>61</ymin>
			<xmax>288</xmax>
			<ymax>144</ymax>
		</bndbox>
	</object>
	<object>
		<name>n</name>
		<pose>Unspecified</pose>
		<truncated>0</truncated>
		<difficult>0</difficult>
		<bndbox>
			<xmin>286</xmin>
			<ymin>59</ymin>
			<xmax>377</xmax>
			<ymax>147</ymax>
		</bndbox>
	</object>
	<object>
		<name>n</name>
		<pose>Unspecified</pose>
		<truncated>0</truncated>
		<difficult>0</difficult>
		<bndbox>
			<xmin>378</xmin>
			<ymin>59</ymin>
			<xmax>454</xmax>
			<ymax>143</ymax>
		</bndbox>
	</object>
	<object>
		<name>e</name>
		<pose>Unspecified</pose>
		<truncated>0</truncated>
		<difficult>0</difficult>
		<bndbox>
			<xmin>455</xmin>
			<ymin>63</ymin>
			<xmax>528</xmax>
			<ymax>136</ymax>
		</bndbox>
	</object>
	<object>
		<name>r</name>
		<pose>Unspecified</pose>
		<truncated>0</truncated>
		<difficult>0</difficult>
		<bndbox>
			<xmin>527</xmin>
			<ymin>65</ymin>
			<xmax>581</xmax>
			<ymax>136</ymax>
		</bndbox>
	</object>
</annotation>
