<annotation>
	<folder>suleiman</folder>
	<filename>5e95b8160e780.jpg</filename>
	<path>/Users/suleimanobeid/Desktop/suleiman/5e95b8160e780.jpg</path>
	<source>
		<database>Unknown</database>
	</source>
	<size>
		<width>800</width>
		<height>200</height>
		<depth>1</depth>
	</size>
	<segmented>0</segmented>
	<object>
		<name>f</name>
		<pose>Unspecified</pose>
		<truncated>0</truncated>
		<difficult>0</difficult>
		<bndbox>
			<xmin>361</xmin>
			<ymin>56</ymin>
			<xmax>421</xmax>
			<ymax>152</ymax>
		</bndbox>
	</object>
	<object>
		<name>l</name>
		<pose>Unspecified</pose>
		<truncated>0</truncated>
		<difficult>0</difficult>
		<bndbox>
			<xmin>421</xmin>
			<ymin>57</ymin>
			<xmax>456</xmax>
			<ymax>147</ymax>
		</bndbox>
	</object>
	<object>
		<name>i</name>
		<pose>Unspecified</pose>
		<truncated>0</truncated>
		<difficult>0</difficult>
		<bndbox>
			<xmin>455</xmin>
			<ymin>51</ymin>
			<xmax>490</xmax>
			<ymax>144</ymax>
		</bndbox>
	</object>
	<object>
		<name>e</name>
		<pose>Unspecified</pose>
		<truncated>0</truncated>
		<difficult>0</difficult>
		<bndbox>
			<xmin>488</xmin>
			<ymin>71</ymin>
			<xmax>567</xmax>
			<ymax>143</ymax>
		</bndbox>
	</object>
	<object>
		<name>s</name>
		<pose>Unspecified</pose>
		<truncated>0</truncated>
		<difficult>0</difficult>
		<bndbox>
			<xmin>568</xmin>
			<ymin>70</ymin>
			<xmax>639</xmax>
			<ymax>148</ymax>
		</bndbox>
	</object>
	<object>
		<name>t</name>
		<pose>Unspecified</pose>
		<truncated>0</truncated>
		<difficult>0</difficult>
		<bndbox>
			<xmin>634</xmin>
			<ymin>62</ymin>
			<xmax>696</xmax>
			<ymax>143</ymax>
		</bndbox>
	</object>
</annotation>
