<annotation>
	<folder></folder>
	<filename>5e95a893c31eb_jpg.rf.5d122d56a3e485db789f19268dd4d4cb.jpg</filename>
	<path>5e95a893c31eb_jpg.rf.5d122d56a3e485db789f19268dd4d4cb.jpg</path>
	<source>
		<database>roboflow.ai</database>
	</source>
	<size>
		<width>782</width>
		<height>194</height>
		<depth>3</depth>
	</size>
	<segmented>0</segmented>
	<object>
		<name>a</name>
		<pose>Unspecified</pose>
		<truncated>0</truncated>
		<difficult>0</difficult>
		<occluded>0</occluded>
		<bndbox>
			<xmin>290</xmin>
			<xmax>388</xmax>
			<ymin>42</ymin>
			<ymax>128</ymax>
		</bndbox>
	</object>
	<object>
		<name>h</name>
		<pose>Unspecified</pose>
		<truncated>0</truncated>
		<difficult>0</difficult>
		<occluded>0</occluded>
		<bndbox>
			<xmin>383</xmin>
			<xmax>467</xmax>
			<ymin>28</ymin>
			<ymax>130</ymax>
		</bndbox>
	</object>
	<object>
		<name>i</name>
		<pose>Unspecified</pose>
		<truncated>0</truncated>
		<difficult>0</difficult>
		<occluded>0</occluded>
		<bndbox>
			<xmin>461</xmin>
			<xmax>504</xmax>
			<ymin>33</ymin>
			<ymax>130</ymax>
		</bndbox>
	</object>
	<object>
		<name>m</name>
		<pose>Unspecified</pose>
		<truncated>0</truncated>
		<difficult>0</difficult>
		<occluded>0</occluded>
		<bndbox>
			<xmin>499</xmin>
			<xmax>620</xmax>
			<ymin>48</ymin>
			<ymax>131</ymax>
		</bndbox>
	</object>
	<object>
		<name>s</name>
		<pose>Unspecified</pose>
		<truncated>0</truncated>
		<difficult>0</difficult>
		<occluded>0</occluded>
		<bndbox>
			<xmin>615</xmin>
			<xmax>692</xmax>
			<ymin>47</ymin>
			<ymax>130</ymax>
		</bndbox>
	</object>
	<object>
		<name>a</name>
		<pose>Unspecified</pose>
		<truncated>0</truncated>
		<difficult>0</difficult>
		<occluded>0</occluded>
		<bndbox>
			<xmin>686</xmin>
			<xmax>774</xmax>
			<ymin>52</ymin>
			<ymax>133</ymax>
		</bndbox>
	</object>
</annotation>
