<annotation>
	<folder></folder>
	<filename>5e95b27d5175f_jpg.rf.5429ac31d4b70000143ffa9fb59abcba.jpg</filename>
	<path>5e95b27d5175f_jpg.rf.5429ac31d4b70000143ffa9fb59abcba.jpg</path>
	<source>
		<database>roboflow.ai</database>
	</source>
	<size>
		<width>800</width>
		<height>200</height>
		<depth>3</depth>
	</size>
	<segmented>0</segmented>
	<object>
		<name>f</name>
		<pose>Unspecified</pose>
		<truncated>0</truncated>
		<difficult>0</difficult>
		<occluded>0</occluded>
		<bndbox>
			<xmin>267</xmin>
			<xmax>323</xmax>
			<ymin>57</ymin>
			<ymax>152</ymax>
		</bndbox>
	</object>
	<object>
		<name>o</name>
		<pose>Unspecified</pose>
		<truncated>0</truncated>
		<difficult>0</difficult>
		<occluded>0</occluded>
		<bndbox>
			<xmin>329</xmin>
			<xmax>409</xmax>
			<ymin>73</ymin>
			<ymax>148</ymax>
		</bndbox>
	</object>
	<object>
		<name>r</name>
		<pose>Unspecified</pose>
		<truncated>0</truncated>
		<difficult>0</difficult>
		<occluded>0</occluded>
		<bndbox>
			<xmin>410</xmin>
			<xmax>462</xmax>
			<ymin>74</ymin>
			<ymax>140</ymax>
		</bndbox>
	</object>
	<object>
		<name>g</name>
		<pose>Unspecified</pose>
		<truncated>0</truncated>
		<difficult>0</difficult>
		<occluded>0</occluded>
		<bndbox>
			<xmin>462</xmin>
			<xmax>544</xmax>
			<ymin>78</ymin>
			<ymax>160</ymax>
		</bndbox>
	</object>
	<object>
		<name>a</name>
		<pose>Unspecified</pose>
		<truncated>0</truncated>
		<difficult>0</difficult>
		<occluded>0</occluded>
		<bndbox>
			<xmin>545</xmin>
			<xmax>627</xmax>
			<ymin>73</ymin>
			<ymax>144</ymax>
		</bndbox>
	</object>
	<object>
		<name>t</name>
		<pose>Unspecified</pose>
		<truncated>0</truncated>
		<difficult>0</difficult>
		<occluded>0</occluded>
		<bndbox>
			<xmin>632</xmin>
			<xmax>687</xmax>
			<ymin>62</ymin>
			<ymax>144</ymax>
		</bndbox>
	</object>
</annotation>
