<annotation>
	<folder></folder>
	<filename>adroit_jpg.rf.ca77a3b9552fc3eacd17bcf557e6ea4b.jpg</filename>
	<path>adroit_jpg.rf.ca77a3b9552fc3eacd17bcf557e6ea4b.jpg</path>
	<source>
		<database>roboflow.ai</database>
	</source>
	<size>
		<width>800</width>
		<height>200</height>
		<depth>3</depth>
	</size>
	<segmented>0</segmented>
	<object>
		<name>a</name>
		<pose>Unspecified</pose>
		<truncated>0</truncated>
		<difficult>0</difficult>
		<occluded>0</occluded>
		<bndbox>
			<xmin>328</xmin>
			<xmax>408</xmax>
			<ymin>63</ymin>
			<ymax>139</ymax>
		</bndbox>
	</object>
	<object>
		<name>d</name>
		<pose>Unspecified</pose>
		<truncated>0</truncated>
		<difficult>0</difficult>
		<occluded>0</occluded>
		<bndbox>
			<xmin>410</xmin>
			<xmax>497</xmax>
			<ymin>44</ymin>
			<ymax>140</ymax>
		</bndbox>
	</object>
	<object>
		<name>r</name>
		<pose>Unspecified</pose>
		<truncated>0</truncated>
		<difficult>0</difficult>
		<occluded>0</occluded>
		<bndbox>
			<xmin>497</xmin>
			<xmax>558</xmax>
			<ymin>62</ymin>
			<ymax>138</ymax>
		</bndbox>
	</object>
	<object>
		<name>o</name>
		<pose>Unspecified</pose>
		<truncated>0</truncated>
		<difficult>0</difficult>
		<occluded>0</occluded>
		<bndbox>
			<xmin>558</xmin>
			<xmax>632</xmax>
			<ymin>63</ymin>
			<ymax>139</ymax>
		</bndbox>
	</object>
	<object>
		<name>i</name>
		<pose>Unspecified</pose>
		<truncated>0</truncated>
		<difficult>0</difficult>
		<occluded>0</occluded>
		<bndbox>
			<xmin>631</xmin>
			<xmax>665</xmax>
			<ymin>48</ymin>
			<ymax>136</ymax>
		</bndbox>
	</object>
	<object>
		<name>t</name>
		<pose>Unspecified</pose>
		<truncated>0</truncated>
		<difficult>0</difficult>
		<occluded>0</occluded>
		<bndbox>
			<xmin>664</xmin>
			<xmax>723</xmax>
			<ymin>52</ymin>
			<ymax>136</ymax>
		</bndbox>
	</object>
</annotation>
