<annotation>
	<folder></folder>
	<filename>5e95b9169d0de_jpg.rf.a17d5a3a07a0f2d191e1ccb96359363e.jpg</filename>
	<path>5e95b9169d0de_jpg.rf.a17d5a3a07a0f2d191e1ccb96359363e.jpg</path>
	<source>
		<database>roboflow.ai</database>
	</source>
	<size>
		<width>778</width>
		<height>194</height>
		<depth>3</depth>
	</size>
	<segmented>0</segmented>
	<object>
		<name>h</name>
		<pose>Unspecified</pose>
		<truncated>0</truncated>
		<difficult>0</difficult>
		<occluded>0</occluded>
		<bndbox>
			<xmin>305</xmin>
			<xmax>401</xmax>
			<ymin>30</ymin>
			<ymax>144</ymax>
		</bndbox>
	</object>
	<object>
		<name>o</name>
		<pose>Unspecified</pose>
		<truncated>0</truncated>
		<difficult>0</difficult>
		<occluded>0</occluded>
		<bndbox>
			<xmin>392</xmin>
			<xmax>475</xmax>
			<ymin>46</ymin>
			<ymax>138</ymax>
		</bndbox>
	</object>
	<object>
		<name>p</name>
		<pose>Unspecified</pose>
		<truncated>0</truncated>
		<difficult>0</difficult>
		<occluded>0</occluded>
		<bndbox>
			<xmin>479</xmin>
			<xmax>569</xmax>
			<ymin>49</ymin>
			<ymax>156</ymax>
		</bndbox>
	</object>
	<object>
		<name>p</name>
		<pose>Unspecified</pose>
		<truncated>0</truncated>
		<difficult>0</difficult>
		<occluded>0</occluded>
		<bndbox>
			<xmin>564</xmin>
			<xmax>648</xmax>
			<ymin>52</ymin>
			<ymax>148</ymax>
		</bndbox>
	</object>
	<object>
		<name>e</name>
		<pose>Unspecified</pose>
		<truncated>0</truncated>
		<difficult>0</difficult>
		<occluded>0</occluded>
		<bndbox>
			<xmin>643</xmin>
			<xmax>733</xmax>
			<ymin>50</ymin>
			<ymax>131</ymax>
		</bndbox>
	</object>
	<object>
		<name>r</name>
		<pose>Unspecified</pose>
		<truncated>0</truncated>
		<difficult>0</difficult>
		<occluded>0</occluded>
		<bndbox>
			<xmin>728</xmin>
			<xmax>778</xmax>
			<ymin>48</ymin>
			<ymax>136</ymax>
		</bndbox>
	</object>
</annotation>
